README
setup.py
src/protobuf_to_dict.py
src/protobuf_to_dict.egg-info/PKG-INFO
src/protobuf_to_dict.egg-info/SOURCES.txt
src/protobuf_to_dict.egg-info/dependency_links.txt
src/protobuf_to_dict.egg-info/requires.txt
src/protobuf_to_dict.egg-info/top_level.txt