Metadata-Version: 1.0
Name: protobuf-to-dict
Version: 0.0.2
Summary: A teeny Python library for creating Python dicts from protocol buffers. Useful as an intermediate step before serialisation (e.g. to JSON).
Home-page: https://github.com/benhodgson/protobuf-to-dict
Author: Ben Hodgson
Author-email: ben@benhodgson.com
License: Public Domain
Keywords: protobuf,json,dict
Platform: UNKNOWN
Classifier: Programming Language :: Python
Classifier: Development Status :: 4 - Beta
Classifier: Intended Audience :: Developers
Classifier: License :: Public Domain
Classifier: Operating System :: OS Independent
Classifier: Topic :: Software Development :: Libraries :: Python Modules
